setup.py
sparklez/__init__.py
sparklez/sparklez.py
sparklez.egg-info/PKG-INFO
sparklez.egg-info/SOURCES.txt
sparklez.egg-info/dependency_links.txt
sparklez.egg-info/entry_points.txt
sparklez.egg-info/not-zip-safe
sparklez.egg-info/requires.txt
sparklez.egg-info/top_level.txt