Metadata-Version: 1.0
Name: sparklez
Version: 0.1.3
Summary: Npm & Rubygem search
Home-page: http://github.com/nickforsman/sparklez
Author: Niclas Forsman
Author-email: n.forsman@hotmail.com
License: MIT
Platform: UNKNOWN
